{
  "definitions" : {
    "DeleteReferencesResponse" : {
      "description" : "The model for the result of a relationship query.\nUsed to get the relationships of a given entity run.",
      "type" : "object",
      "additionalProperties" : false,
      "properties" : {
        "relatedAspects" : {
          "type" : "array",
          "items" : {
            "$ref" : "#/definitions/RelatedAspect"
          }
        },
        "total" : {
          "description" : "Total number of relationships that an entity urn has.",
          "type" : "integer",
          "minimum" : -2147483648,
          "maximum" : 2147483647
        }
      },
      "required" : [ "relatedAspects", "total" ]
    },
    "RelatedAspect" : {
      "description" : "Metadata about how an aspect is related to some urn",
      "type" : "object",
      "additionalProperties" : false,
      "properties" : {
        "entity" : {
          "description" : " Urn of the entity that is referenced by the aspect.",
          "type" : "string"
        },
        "aspect" : {
          "type" : "string"
        },
        "relationship" : {
          "type" : "string"
        }
      },
      "required" : [ "entity", "aspect", "relationship" ]
    }
  },
  "$ref" : "#/definitions/DeleteReferencesResponse"
}