{
  "definitions" : {
    "MLPrimaryKeyKey" : {
      "description" : "Key for an MLPrimaryKey",
      "type" : "object",
      "additionalProperties" : false,
      "properties" : {
        "featureNamespace" : {
          "description" : "Namespace for the primary key",
          "type" : "string"
        },
        "name" : {
          "description" : "Name of the primary key",
          "type" : "string"
        }
      },
      "required" : [ "featureNamespace", "name" ]
    }
  },
  "$ref" : "#/definitions/MLPrimaryKeyKey"
}