{
  "definitions" : {
    "MLPrimaryKeySnapshot" : {
      "type" : "object",
      "additionalProperties" : false,
      "properties" : {
        "urn" : {
          "description" : "URN for the entity the metadata snapshot is associated with.",
          "type" : "string"
        },
        "aspects" : {
          "description" : "The list of metadata aspects associated with the MLPrimaryKey. Depending on the use case, this can either be all, or a selection, of supported aspects.",
          "type" : "array",
          "items" : {
            "oneOf" : [ {
              "$ref" : "#/definitions/MLPrimaryKeyKey"
            }, {
              "$ref" : "#/definitions/MLPrimaryKeyProperties"
            }, {
              "$ref" : "#/definitions/Ownership"
            }, {
              "$ref" : "#/definitions/InstitutionalMemory"
            }, {
              "$ref" : "#/definitions/Status"
            }, {
              "$ref" : "#/definitions/Deprecation"
            }, {
              "$ref" : "#/definitions/GlobalTags"
            }, {
              "$ref" : "#/definitions/DataPlatformInstance"
            } ]
          }
        }
      },
      "required" : [ "urn", "aspects" ]
    },
    "MLPrimaryKeyKey" : {
      "description" : "Key for an MLPrimaryKey",
      "type" : "object",
      "additionalProperties" : false,
      "properties" : {
        "featureNamespace" : {
          "description" : "Namespace for the primary key",
          "type" : "string"
        },
        "name" : {
          "description" : "Name of the primary key",
          "type" : "string"
        }
      },
      "required" : [ "featureNamespace", "name" ]
    },
    "MLPrimaryKeyProperties" : {
      "description" : "Properties associated with a MLPrimaryKey",
      "type" : "object",
      "additionalProperties" : false,
      "properties" : {
        "customProperties" : {
          "default" : { },
          "description" : "Custom property bag.",
          "type" : "object",
          "additionalProperties" : {
            "type" : "string"
          }
        },
        "description" : {
          "default" : null,
          "description" : "Documentation of the MLPrimaryKey",
          "type" : "string"
        },
        "dataType" : {
          "default" : null,
          "description" : "Data Type of the MLPrimaryKey",
          "$ref" : "#/definitions/MLFeatureDataType"
        },
        "version" : {
          "default" : null,
          "description" : "Version of the MLPrimaryKey",
          "$ref" : "#/definitions/VersionTag"
        },
        "sources" : {
          "description" : "Source of the MLPrimaryKey",
          "type" : "array",
          "items" : {
            "type" : "string"
          }
        }
      },
      "required" : [ "customProperties", "sources" ]
    },
    "MLFeatureDataType" : {
      "description" : "MLFeature Data Type",
      "enum" : [ "USELESS", "NOMINAL", "ORDINAL", "BINARY", "COUNT", "TIME", "INTERVAL", "IMAGE", "VIDEO", "AUDIO", "TEXT", "MAP", "SEQUENCE", "SET", "CONTINUOUS", "BYTE", "UNKNOWN" ]
    },
    "VersionTag" : {
      "description" : "A resource-defined string representing the resource state for the purpose of concurrency control",
      "type" : "object",
      "additionalProperties" : false,
      "properties" : {
        "versionTag" : {
          "default" : null,
          "type" : "string"
        },
        "metadataAttribution" : {
          "default" : null,
          "$ref" : "#/definitions/MetadataAttribution"
        }
      }
    },
    "MetadataAttribution" : {
      "description" : "Information about who, why, and how this metadata was applied",
      "type" : "object",
      "additionalProperties" : false,
      "properties" : {
        "time" : {
          "description" : "When this metadata was updated.",
          "type" : "integer",
          "format" : "int64",
          "minimum" : -9223372036854775808,
          "maximum" : 9223372036854775807
        },
        "actor" : {
          "description" : "The entity (e.g. a member URN) responsible for applying the assocated metadata. This can\neither be a user (in case of UI edits) or the datahub system for automation.",
          "type" : "string"
        },
        "source" : {
          "default" : null,
          "description" : "The DataHub source responsible for applying the associated metadata. This will only be filled out\nwhen a DataHub source is responsible. This includes the specific metadata test urn, the automation urn.",
          "type" : "string"
        },
        "sourceDetail" : {
          "default" : { },
          "description" : "The details associated with why this metadata was applied. For example, this could include\nthe actual regex rule, sql statement, ingestion pipeline ID, etc.",
          "type" : "object",
          "additionalProperties" : {
            "type" : "string"
          }
        }
      },
      "required" : [ "time", "actor", "sourceDetail" ]
    },
    "Ownership" : {
      "description" : "Ownership information of an entity.",
      "type" : "object",
      "additionalProperties" : false,
      "properties" : {
        "owners" : {
          "description" : "List of owners of the entity.",
          "type" : "array",
          "items" : {
            "$ref" : "#/definitions/Owner"
          }
        },
        "ownerTypes" : {
          "default" : { },
          "description" : "Ownership type to Owners map, populated via mutation hook.",
          "type" : "object",
          "additionalProperties" : {
            "type" : "array",
            "items" : {
              "type" : "string"
            }
          }
        },
        "lastModified" : {
          "default" : {
            "actor" : "urn:li:corpuser:unknown",
            "impersonator" : null,
            "time" : 0,
            "message" : null
          },
          "description" : "Audit stamp containing who last modified the record and when. A value of 0 in the time field indicates missing data.",
          "$ref" : "#/definitions/AuditStamp"
        }
      },
      "required" : [ "owners", "ownerTypes", "lastModified" ]
    },
    "Owner" : {
      "description" : "Ownership information",
      "type" : "object",
      "additionalProperties" : false,
      "properties" : {
        "owner" : {
          "description" : "Owner URN, e.g. urn:li:corpuser:ldap, urn:li:corpGroup:group_name, and urn:li:multiProduct:mp_name\n(Caveat: only corpuser is currently supported in the frontend.)",
          "type" : "string"
        },
        "type" : {
          "description" : "The type of the ownership",
          "$ref" : "#/definitions/OwnershipType"
        },
        "typeUrn" : {
          "default" : null,
          "description" : "The type of the ownership\nUrn of type O",
          "type" : "string"
        },
        "source" : {
          "default" : null,
          "description" : "Source information for the ownership",
          "$ref" : "#/definitions/OwnershipSource"
        },
        "attribution" : {
          "default" : null,
          "description" : "Information about who, why, and how this metadata was applied",
          "$ref" : "#/definitions/MetadataAttribution"
        }
      },
      "required" : [ "owner", "type" ]
    },
    "OwnershipType" : {
      "description" : "Asset owner types",
      "enum" : [ "CUSTOM", "TECHNICAL_OWNER", "BUSINESS_OWNER", "DATA_STEWARD", "NONE", "DEVELOPER", "DATAOWNER", "DELEGATE", "PRODUCER", "CONSUMER", "STAKEHOLDER" ]
    },
    "OwnershipSource" : {
      "description" : "Source/provider of the ownership information",
      "type" : "object",
      "additionalProperties" : false,
      "properties" : {
        "type" : {
          "description" : "The type of the source",
          "$ref" : "#/definitions/OwnershipSourceType"
        },
        "url" : {
          "default" : null,
          "description" : "A reference URL for the source",
          "type" : "string"
        }
      },
      "required" : [ "type" ]
    },
    "OwnershipSourceType" : {
      "enum" : [ "AUDIT", "DATABASE", "FILE_SYSTEM", "ISSUE_TRACKING_SYSTEM", "MANUAL", "SERVICE", "SOURCE_CONTROL", "OTHER" ]
    },
    "AuditStamp" : {
      "description" : "Data captured on a resource/association/sub-resource level giving insight into when that resource/association/sub-resource moved into a particular lifecycle stage, and who acted to move it into that specific lifecycle stage.",
      "type" : "object",
      "additionalProperties" : false,
      "properties" : {
        "time" : {
          "description" : "When did the resource/association/sub-resource move into the specific lifecycle stage represented by this AuditEvent.",
          "type" : "integer",
          "format" : "int64",
          "minimum" : -9223372036854775808,
          "maximum" : 9223372036854775807
        },
        "actor" : {
          "description" : "The entity (e.g. a member URN) which will be credited for moving the resource/association/sub-resource into the specific lifecycle stage. It is also the one used to authorize the change.",
          "type" : "string"
        },
        "impersonator" : {
          "default" : null,
          "description" : "The entity (e.g. a service URN) which performs the change on behalf of the Actor and must be authorized to act as the Actor.",
          "type" : "string"
        },
        "message" : {
          "default" : null,
          "description" : "Additional context around how DataHub was informed of the particular change. For example: was the change created by an automated process, or manually.",
          "type" : "string"
        }
      },
      "required" : [ "time", "actor" ]
    },
    "InstitutionalMemory" : {
      "description" : "Institutional memory of an entity. This is a way to link to relevant documentation and provide description of the documentation. Institutional or tribal knowledge is very important for users to leverage the entity.",
      "type" : "object",
      "additionalProperties" : false,
      "properties" : {
        "elements" : {
          "description" : "List of records that represent institutional memory of an entity. Each record consists of a link, description, creator and timestamps associated with that record.",
          "type" : "array",
          "items" : {
            "$ref" : "#/definitions/InstitutionalMemoryMetadata"
          }
        }
      },
      "required" : [ "elements" ]
    },
    "InstitutionalMemoryMetadata" : {
      "description" : "Metadata corresponding to a record of institutional memory.",
      "type" : "object",
      "additionalProperties" : false,
      "properties" : {
        "url" : {
          "description" : "Link to an engineering design document or a wiki page.",
          "type" : "string"
        },
        "description" : {
          "description" : "Description of the link.",
          "type" : "string"
        },
        "createStamp" : {
          "description" : "Audit stamp associated with creation of this record",
          "$ref" : "#/definitions/AuditStamp"
        },
        "updateStamp" : {
          "default" : null,
          "description" : "Audit stamp associated with updation of this record",
          "$ref" : "#/definitions/AuditStamp"
        },
        "settings" : {
          "default" : null,
          "description" : "Settings for this record",
          "$ref" : "#/definitions/InstitutionalMemoryMetadataSettings"
        }
      },
      "required" : [ "url", "description", "createStamp" ]
    },
    "InstitutionalMemoryMetadataSettings" : {
      "description" : "Settings related to a record of InstitutionalMemoryMetadata",
      "type" : "object",
      "additionalProperties" : false,
      "properties" : {
        "showInAssetPreview" : {
          "default" : false,
          "description" : "Show record in asset preview like on entity header and search previews",
          "type" : "boolean"
        }
      },
      "required" : [ "showInAssetPreview" ]
    },
    "Status" : {
      "description" : "The lifecycle status metadata of an entity, e.g. dataset, metric, feature, etc.\nThis aspect is used to represent soft deletes conventionally.",
      "type" : "object",
      "additionalProperties" : false,
      "properties" : {
        "removed" : {
          "default" : false,
          "description" : "Whether the entity has been removed (soft-deleted).",
          "type" : "boolean"
        }
      },
      "required" : [ "removed" ]
    },
    "Deprecation" : {
      "description" : "Deprecation status of an entity",
      "type" : "object",
      "additionalProperties" : false,
      "properties" : {
        "deprecated" : {
          "description" : "Whether the entity is deprecated.",
          "type" : "boolean"
        },
        "decommissionTime" : {
          "default" : null,
          "description" : "The time user plan to decommission this entity.",
          "type" : "integer",
          "format" : "int64",
          "minimum" : -9223372036854775808,
          "maximum" : 9223372036854775807
        },
        "note" : {
          "description" : "Additional information about the entity deprecation plan, such as the wiki, doc, RB.",
          "type" : "string"
        },
        "actor" : {
          "description" : "The user URN which will be credited for modifying this deprecation content.",
          "type" : "string"
        },
        "replacement" : {
          "default" : null,
          "type" : "string"
        }
      },
      "required" : [ "deprecated", "note", "actor" ]
    },
    "GlobalTags" : {
      "description" : "Tag aspect used for applying tags to an entity",
      "type" : "object",
      "additionalProperties" : false,
      "properties" : {
        "tags" : {
          "description" : "Tags associated with a given entity",
          "type" : "array",
          "items" : {
            "$ref" : "#/definitions/TagAssociation"
          }
        }
      },
      "required" : [ "tags" ]
    },
    "TagAssociation" : {
      "description" : "Properties of an applied tag. For now, just an Urn. In the future we can extend this with other properties, e.g.\npropagation parameters.",
      "type" : "object",
      "additionalProperties" : false,
      "properties" : {
        "tag" : {
          "description" : "Urn of the applied tag",
          "type" : "string"
        },
        "context" : {
          "default" : null,
          "description" : "Additional context about the association",
          "type" : "string"
        },
        "attribution" : {
          "default" : null,
          "description" : "Information about who, why, and how this metadata was applied",
          "$ref" : "#/definitions/MetadataAttribution"
        }
      },
      "required" : [ "tag" ]
    },
    "DataPlatformInstance" : {
      "description" : "The specific instance of the data platform that this entity belongs to",
      "type" : "object",
      "additionalProperties" : false,
      "properties" : {
        "platform" : {
          "description" : "Data Platform",
          "type" : "string"
        },
        "instance" : {
          "default" : null,
          "description" : "Instance of the data platform (e.g. db instance)",
          "type" : "string"
        }
      },
      "required" : [ "platform" ]
    }
  },
  "$ref" : "#/definitions/MLPrimaryKeySnapshot"
}