{
  "definitions" : {
    "SlackUserInfo" : {
      "description" : "Information about a Slack user.",
      "type" : "object",
      "additionalProperties" : false,
      "properties" : {
        "slackInstance" : {
          "description" : "The dataplatform instance that this Slack member belongs to.",
          "type" : "string"
        },
        "id" : {
          "description" : "The unique identifier for the Slack member.",
          "type" : "string"
        },
        "name" : {
          "description" : "The username of the Slack member.",
          "type" : "string"
        },
        "realName" : {
          "description" : "The real name of the Slack member.",
          "type" : "string"
        },
        "displayName" : {
          "description" : "The display name of the Slack member.",
          "type" : "string"
        },
        "email" : {
          "default" : null,
          "description" : "The email associated with the Slack member.",
          "type" : "string"
        },
        "teamId" : {
          "description" : "The ID associated with the Slack team.",
          "type" : "string"
        },
        "isDeleted" : {
          "description" : "Whether the member is deleted or not.",
          "type" : "boolean"
        },
        "isAdmin" : {
          "description" : "Whether the member is an admin.",
          "type" : "boolean"
        },
        "isOwner" : {
          "description" : "Whether the member is an owner.",
          "type" : "boolean"
        },
        "isPrimaryOwner" : {
          "description" : "Whether the member is a primary owner.",
          "type" : "boolean"
        },
        "isBot" : {
          "description" : "Whether the member is a bot.",
          "type" : "boolean"
        },
        "timezone" : {
          "default" : null,
          "description" : "The timezone of the Slack member.",
          "type" : "string"
        },
        "timezoneOffset" : {
          "default" : null,
          "description" : "The timezone offset of the Slack member.",
          "type" : "integer",
          "minimum" : -2147483648,
          "maximum" : 2147483647
        },
        "title" : {
          "default" : null,
          "description" : "The title of the Slack member.",
          "type" : "string"
        },
        "phone" : {
          "default" : null,
          "description" : "The phone number of the Slack member.",
          "type" : "string"
        },
        "profilePictureUrl" : {
          "default" : null,
          "description" : "The URL of the member's profile picture.",
          "type" : "string"
        },
        "statusText" : {
          "default" : null,
          "description" : "The status text of the Slack member.",
          "type" : "string"
        },
        "statusEmoji" : {
          "default" : null,
          "description" : "The status emoji of the Slack member.",
          "type" : "string"
        },
        "lastUpdatedSeconds" : {
          "default" : null,
          "description" : "The timestamp of when the member was last updated. (in seconds)",
          "type" : "integer",
          "format" : "int64",
          "minimum" : -9223372036854775808,
          "maximum" : 9223372036854775807
        }
      },
      "required" : [ "slackInstance", "id", "name", "realName", "displayName", "teamId", "isDeleted", "isAdmin", "isOwner", "isPrimaryOwner", "isBot" ]
    }
  },
  "$ref" : "#/definitions/SlackUserInfo"
}